nni/__init__.py
nni/__main__.py
nni/assessor.py
nni/common.py
nni/constants.py
nni/msg_dispatcher.py
nni/msg_dispatcher_base.py
nni/parameter_expressions.py
nni/protocol.py
nni/recoverable.py
nni/smartparam.py
nni/trial.py
nni/tuner.py
nni/batch_tuner/__init__.py
nni/batch_tuner/batch_tuner.py
nni/evolution_tuner/__init__.py
nni/evolution_tuner/evolution_tuner.py
nni/gridsearch_tuner/__init__.py
nni/gridsearch_tuner/gridsearch_tuner.py
nni/hyperband_advisor/__init__.py
nni/hyperband_advisor/hyperband_advisor.py
nni/hyperband_advisor/requirements.txt
nni/hyperopt_tuner/__init__.py
nni/hyperopt_tuner/hyperopt_tuner.py
nni/medianstop_assessor/__init__.py
nni/medianstop_assessor/medianstop_assessor.py
nni/medianstop_assessor/test.py
nni/multi_phase/__init__.py
nni/multi_phase/multi_phase_dispatcher.py
nni/multi_phase/multi_phase_tuner.py
nni/platform/__init__.py
nni/platform/local.py
nni/platform/standalone.py
nni/platform/test.py
nni/smac_tuner/__init__.py
nni/smac_tuner/convert_ss_to_scenario.py
nni/smac_tuner/requirements.txt
nni/smac_tuner/smac_tuner.py
nni_sdkv04-0.4.1.dist-info/DESCRIPTION.rst
nni_sdkv04-0.4.1.dist-info/METADATA
nni_sdkv04-0.4.1.dist-info/RECORD
nni_sdkv04-0.4.1.dist-info/WHEEL
nni_sdkv04-0.4.1.dist-info/metadata.json
nni_sdkv04-0.4.1.dist-info/top_level.txt
